tests/configuration/__init__.py
tests/configuration/hello_world/__init__.py
tests/configuration/hello_world/test_config.py
tests/configuration/hello_world/test_main.py
tests/configuration/hello_world/test_parse_punctuation.py
tests/configuration/parser/__init__.py
tests/configuration/parser/test_parse_config.py
tests/configuration/printing/__init__.py
tests/configuration/printing/test_config_printing.py
tests/configuration/printing/test_recursive_object_printing.py
vr_configuration/__init__.py
vr_configuration/paths.py
vr_configuration/py.typed
vr_configuration/hello_world/__init__.py
vr_configuration/hello_world/config.py
vr_configuration/hello_world/config_with_punctuation.py
vr_configuration/hello_world/main.py
vr_configuration/hello_world/parse_punctuation.py
vr_configuration/hello_world/paths.py
vr_configuration/hello_world/punctuation_enum.py
vr_configuration/parser/__init__.py
vr_configuration/parser/_create_potentially_nested_type.py
vr_configuration/parser/_create_type.py
vr_configuration/parser/_sub_config_getting.py
vr_configuration/parser/_type_class.py
vr_configuration/parser/config_parsing.py
vr_configuration/parser/enumeration_parsing.py
vr_configuration/printing/__init__.py
vr_configuration/printing/configuration_printing.py
vr_configuration/printing/recursive_dumping.py
vr_configuration/printing/recursive_object_printing.py
vr_configuration/shims/__init__.py
vr_configuration/shims/path/__init__.py
vr_configuration/shims/path/path_ensuring.py
vr_configuration-1.1.27.dist-info/METADATA
vr_configuration-1.1.27.dist-info/WHEEL
vr_configuration-1.1.27.dist-info/top_level.txt
vr_configuration-1.1.27.dist-info/RECORD
